tree_sitter_tlaplus/__init__.pyi
tree_sitter_tlaplus/binding.c
tree_sitter_tlaplus/__init__.py
tree_sitter_tlaplus/py.typed
tree_sitter_tlaplus/_binding.abi3.so
tree_sitter_tlaplus/queries/locals.scm
tree_sitter_tlaplus/queries/highlights.scm
tree_sitter_tlaplus-1.5.0.dist-info/RECORD
tree_sitter_tlaplus-1.5.0.dist-info/LICENSE
tree_sitter_tlaplus-1.5.0.dist-info/WHEEL
tree_sitter_tlaplus-1.5.0.dist-info/top_level.txt
tree_sitter_tlaplus-1.5.0.dist-info/METADATA
