Metadata-Version: 2.1
Name: tree-sitter-tlaplus
Version: 1.5.0
Summary: A tree-sitter grammar for TLA⁺ and PlusCal
Author: Andrew Helwer, Vasiliy Morkovkin
Maintainer: Andrew Helwer
License: MIT
Project-URL: Homepage, https://github.com/tlaplus-community/tree-sitter-tlaplus
Project-URL: Issues, https://github.com/tlaplus-community/tree-sitter-tlaplus/issues
Keywords: incremental,parsing,tree-sitter,tlaplus
Classifier: Intended Audience :: Developers
Classifier: License :: OSI Approved :: MIT License
Classifier: Topic :: Software Development :: Compilers
Classifier: Topic :: Text Processing :: Linguistic
Classifier: Typing :: Typed
Requires-Python: >=3.8
License-File: LICENSE
Provides-Extra: core
Requires-Dist: tree-sitter ~=0.22 ; extra == 'core'
